unboil_pywalker/__init__.py
unboil_pywalker-0.1.4.dist-info/METADATA
unboil_pywalker-0.1.4.dist-info/WHEEL
unboil_pywalker-0.1.4.dist-info/licenses/LICENSE
unboil_pywalker-0.1.4.dist-info/RECORD
